portpy/__init__.py
portpy/ai/__init__.py
portpy/ai/test.py
portpy/ai/train.py
portpy/ai/data/__init__.py
portpy/ai/data/base_dataset.py
portpy/ai/data/dosepred3d_dataset.py
portpy/ai/data/image_folder.py
portpy/ai/data/single_dataset.py
portpy/ai/data/template_dataset.py
portpy/ai/models/__init__.py
portpy/ai/models/base_model.py
portpy/ai/models/doseprediction3d_model.py
portpy/ai/models/networks3d.py
portpy/ai/models/test_model.py
portpy/ai/options/__init__.py
portpy/ai/options/base_options.py
portpy/ai/options/test_options.py
portpy/ai/options/train_options.py
portpy/ai/preprocess/data_preprocess.py
portpy/ai/preprocess/pred_dose_to_original_portpy.py
portpy/ai/preprocess/predict_using_model.py
portpy/ai/statistics/compute_dvh_stats.py
portpy/ai/util/__init__.py
portpy/ai/util/html.py
portpy/ai/util/image_pool.py
portpy/ai/util/util.py
portpy/ai/util/visualizer.py
portpy/config_files/__init__.py
portpy/config_files/clinical_criteria/Default/Lung_2Gy_30Fx.json
portpy/config_files/clinical_criteria/Default/Paraspinal_1Fx.json
portpy/config_files/clinical_criteria/Default/Prostate_26Fx.json
portpy/config_files/optimization_params/optimization_params_Lung_2Gy_30Fx.json
portpy/config_files/optimization_params/optimization_params_Lung_2Gy_30Fx_vmat.json
portpy/config_files/optimization_params/optimization_params_Paraspinal_1Fx.json
portpy/config_files/optimization_params/optimization_params_Prostate_26Fx.json
portpy/config_files/tcia_patients/tcia_patients_metadata.json
portpy/photon/__init__.py
portpy/photon/beam.py
portpy/photon/clinical_criteria.py
portpy/photon/ct.py
portpy/photon/data_explorer.py
portpy/photon/evaluation.py
portpy/photon/influence_matrix.py
portpy/photon/optimization.py
portpy/photon/plan.py
portpy/photon/structures.py
portpy/photon/visualization.py
portpy/photon/utils/__init__.py
portpy/photon/utils/convert_dose_rt_dicom_to_portpy.py
portpy/photon/utils/create_ct_dose_voxel_map.py
portpy/photon/utils/get_apt_reg_metric.py
portpy-1.1.2.dist-info/licenses/LICENSE.txt
portpy-1.1.2.dist-info/METADATA
portpy-1.1.2.dist-info/WHEEL
portpy-1.1.2.dist-info/top_level.txt
portpy-1.1.2.dist-info/RECORD
