Metadata-Version: 2.4
Name: portpy
Version: 1.1.2
Summary: First open-source radiation treatment planning system in Python
Author-email: Gourav Jhanwar <jhanwarg@mskcc.org>, Mojtaba Tefagh <mtefagh@sharif.edu>, Vicki Taasti <vicki.taasti@maastro.nl>, Seppo Tuomaala <tuomaals@mskcc.org>, Saad Nadeem <nadeems@mskcc.org>, Masoud Zarepisheh <zarepism@mskcc.org>
License-Expression: Apache-2.0
Project-URL: Homepage, https://github.com/PortPy-Project/PortPy
Classifier: Development Status :: 1 - Planning
Classifier: Intended Audience :: Science/Research
Classifier: Programming Language :: Python :: 3.9
Classifier: Topic :: Scientific/Engineering :: Mathematics
Requires-Python: >=3.8
License-File: LICENSE.txt
Requires-Dist: cvxpy>=1.1.18
Requires-Dist: ecos>=2.0.10
Requires-Dist: h5py>=3.6.0
Requires-Dist: natsort>=8.1.0
Requires-Dist: numpy>=1.15
Requires-Dist: pandas>=1.1.5
Requires-Dist: python-dateutil>=2.8.2
Requires-Dist: pytz>=2022.1
Requires-Dist: qdldl>=0.1.5
Requires-Dist: scipy>=1.5.4
Requires-Dist: scs>=3.2.0
Requires-Dist: six>=1.16.0
Requires-Dist: matplotlib>=3.5.3
Requires-Dist: Shapely>=1.8.4
Requires-Dist: SimpleITK>=2.0.2
Requires-Dist: tabulate>=0.9.0
Requires-Dist: jinja2==3.1.5
Requires-Dist: typing-extensions>=3.10.0.0
Requires-Dist: scikit-image>=0.17.2
Requires-Dist: patchify>=0.2.3
Provides-Extra: mosek
Requires-Dist: Mosek>=9.3.14; extra == "mosek"
Provides-Extra: pydicom
Requires-Dist: pydicom>=2.2.0; extra == "pydicom"
Provides-Extra: all
Requires-Dist: Mosek>=9.3.14; extra == "all"
Requires-Dist: pydicom>=2.2.0; extra == "all"
Requires-Dist: websocket-client>=1.8.0; extra == "all"
Requires-Dist: visdom>=0.2.4; extra == "all"
Requires-Dist: dominate>=2.6.0; extra == "all"
Requires-Dist: torch>=2.7.0; extra == "all"
Requires-Dist: torchfile>=0.1.0; extra == "all"
Requires-Dist: torchvision>=0.9.1; extra == "all"
Requires-Dist: huggingface-hub>=0.34.3; extra == "all"
Provides-Extra: test
Requires-Dist: pytest>=8.0; extra == "test"
Requires-Dist: huggingface-hub>=0.34.3; extra == "test"
Provides-Extra: ai
Requires-Dist: websocket-client>=1.8.0; extra == "ai"
Requires-Dist: visdom>=0.2.4; extra == "ai"
Requires-Dist: dominate>=2.6.0; extra == "ai"
Requires-Dist: torch>=2.7.0; extra == "ai"
Requires-Dist: torchfile>=0.1.0; extra == "ai"
Requires-Dist: torchvision>=0.9.1; extra == "ai"
Dynamic: license-file
